{"nodes":[{"title":"Install / Update PaperMod","url":"/posts/papermod/papermod-installation/"},{"title":"Features / Mods","url":"/posts/papermod/papermod-features/"},{"title":"Markdown Syntax Guide For L2","url":"/posts/markdown-syntax.fr/"},{"title":"Markdown Syntax Guide For RTL","url":"/posts/markdown-syntax.fa/"},{"title":"Markdown Syntax Guide","url":"/posts/markdown-syntax/"},{"title":"Code Syntax Guide","url":"/posts/code_syntax/"},{"title":"Math Typesetting","url":"/posts/math-typesetting/"},{"title":"Emoji Support","url":"/posts/emoji-support/"}]}